majormode/__init__.py
majormode/perseus/__init__.py
majormode/perseus/model/__init__.py
majormode/perseus/model/microrm.py
majormode/perseus/utils/__init__.py
majormode/perseus/utils/rdbms.py
perseus_microrm_library-1.3.9.dist-info/LICENSE.md
perseus_microrm_library-1.3.9.dist-info/WHEEL
perseus_microrm_library-1.3.9.dist-info/METADATA
perseus_microrm_library-1.3.9.dist-info/RECORD
