Metadata-Version: 2.1
Name: perseus-microrm-library
Version: 1.3.9
Summary: Python small, little, mini, tiny, micro Object-Relational Mapping (ORM)
Home-page: https://github.com/majormode/perseus-microrm-python-library
License: SEE LICENSE IN <LICENSE.md>
Keywords: micro,orm,libray,postgresql,rdbms
Author: Daniel CAUNE
Author-email: daniel.caune@gmail.com
Requires-Python: >=3.9
Classifier: Development Status :: 5 - Production/Stable
Classifier: License :: Other/Proprietary License
Classifier: Operating System :: OS Independent
Classifier: Programming Language :: Python
Classifier: Programming Language :: Python :: 3
Classifier: Programming Language :: Python :: 3.9
Classifier: Programming Language :: Python :: 3.10
Classifier: Programming Language :: Python :: 3.11
Classifier: Topic :: Software Development :: Libraries
Requires-Dist: perseus-core-library (>=1.20.4,<2.0.0)
Requires-Dist: psycopg2-binary (>=2.9.9,<3.0.0)
Project-URL: Repository, https://github.com/majormode/perseus-microrm-python-library
